aesedb/__init__.py
aesedb/_version.py
aesedb/eesentdb.py
aesedb/constants/__init__.py
aesedb/constants/colnames.py
aesedb/examples/__init__.py
aesedb/examples/ntdsparse.py
aesedb/security/__init__.py
aesedb/security/constants.py
aesedb/security/ntds.py
aesedb/security/common/__init__.py
aesedb/security/common/usersecret.py
aesedb/security/structures/__init__.py
aesedb/security/structures/crypted.py
aesedb/security/structures/kerbsecret.py
aesedb/security/structures/pek.py
aesedb/security/structures/sid.py
aesedb/security/structures/userprops.py
aesedb/structures/__init__.py
aesedb/structures/branchentry.py
aesedb/structures/branchheader.py
aesedb/structures/catalogdatadefentry.py
aesedb/structures/datadefinitionheader.py
aesedb/structures/header.py
aesedb/structures/indexentry.py
aesedb/structures/jetsignature.py
aesedb/structures/leafentry.py
aesedb/structures/leafheader.py
aesedb/structures/page.py
aesedb/structures/pageheader.py
aesedb/structures/rootheader.py
aesedb/structures/spacetreeentry.py
aesedb/structures/spacetreeheader.py
aesedb/utils/__init__.py
aesedb/utils/afile.py
aesedb/utils/hexdump.py
aesedb/utils/systemhive.py
aesedb-0.1.7.dist-info/licenses/LICENSE
aesedb-0.1.7.dist-info/METADATA
aesedb-0.1.7.dist-info/WHEEL
aesedb-0.1.7.dist-info/entry_points.txt
aesedb-0.1.7.dist-info/top_level.txt
aesedb-0.1.7.dist-info/zip-safe
aesedb-0.1.7.dist-info/RECORD
