Metadata-Version: 2.4
Name: aesedb
Version: 0.1.7
Summary: NTDS parser toolkit
Home-page: https://github.com/skelsec/aesedb
Author: Tamas Jos
Author-email: info@skelsecprojects.com
License: Modified Apache Software License 1.1
Classifier: Programming Language :: Python :: 3.6
Classifier: Operating System :: OS Independent
Requires-Python: >=3.6
License-File: LICENSE
Requires-Dist: unicrypto>=0.0.11
Requires-Dist: aiowinreg>=0.0.12
Requires-Dist: tqdm
Requires-Dist: colorama
Dynamic: author
Dynamic: author-email
Dynamic: classifier
Dynamic: home-page
Dynamic: license
Dynamic: license-file
Dynamic: requires-dist
Dynamic: requires-python
Dynamic: summary
